AUTHORS.rst
CONTRIBUTING.rst
HISTORY.rst
LICENSE
MANIFEST.in
README.rst
setup.cfg
setup.py
docs/Makefile
docs/authors.rst
docs/conf.py
docs/contributing.rst
docs/history.rst
docs/index.rst
docs/installation.rst
docs/make.bat
docs/readme.rst
docs/usage.rst
pisco_sour.egg-info/PKG-INFO
pisco_sour.egg-info/SOURCES.txt
pisco_sour.egg-info/dependency_links.txt
pisco_sour.egg-info/not-zip-safe
pisco_sour.egg-info/top_level.txt
plushcap/__init__.py
plushcap/plushcap.py
tests/__init__.py
tests/old_test_plushcap.py
tests/test_plushcap.py