Metadata-Version: 1.1
Name: pisco-sour
Version: 0.1.0
Summary: Plushcap monitors websites and alerts people via text or phone call if there is a problem.
Home-page: https://github.com/mickstevens/plushcap
Author: Mick Stevens
Author-email: mickstevens@yahoo.com
License: BSD
Keywords: plushcap
Platform: UNKNOWN
Classifier: Development Status :: 2 - Pre-Alpha
Classifier: Intended Audience :: Developers
Classifier: License :: OSI Approved :: BSD License
Classifier: Natural Language :: English
Classifier: Programming Language :: Python :: 2
Classifier: Programming Language :: Python :: 2.6
Classifier: Programming Language :: Python :: 2.7
Classifier: Programming Language :: Python :: 3
Classifier: Programming Language :: Python :: 3.3
Classifier: Programming Language :: Python :: 3.4
